[{"arguments":["clang","-Wno-documentation-unknown-command","-Wno-unknown-warning-option","-Wno-unknown-pragmas","-nostdinc","-nostdinc++","-std=gnu++1z","-Wall","-Wextra","-Wextra","-fexceptions","-mthreads","-fsyntax-only","-m64","--target=x86_64-w64-mingw32","-DUNICODE","-D_UNICODE","-DWIN32","-DMINGW_HAS_SECURE_API","-DQT_NO_DEBUG","-DQT_WIDGETS_LIB","-DQT_GUI_LIB","-DQT_CORE_LIB","-DQT_NEEDS_QMAIN","-DQ_CREATOR_RUN","-DQT_ANNOTATE_FUNCTION(x)=__attribute__((annotate(#x)))","-ID:\\App\\Qt\\Tools\\QtCreator\\share\\qtcreator\\cplusplus\\wrappedMingwHeaders","-ID:\\App\\Qt\\Tools\\QtCreator\\share\\qtcreator\\cplusplus\\wrappedQtHeaders","-ID:\\App\\Qt\\Tools\\QtCreator\\share\\qtcreator\\cplusplus\\wrappedQtHeaders\\QtCore","-ID:\\Coding\\Qt\\StudentMessageManagemantSystem","-ID:\\App\\Qt\\6.9.2\\mingw_64\\include","-ID:\\App\\Qt\\6.9.2\\mingw_64\\include\\QtWidgets","-ID:\\App\\Qt\\6.9.2\\mingw_64\\include\\QtGui","-ID:\\App\\Qt\\6.9.2\\mingw_64\\include\\QtCore","-ID:\\Coding\\Qt\\StudentMessageManagemantSystem\\build\\Desktop_Qt_6_9_2_MinGW_64_bit-Release\\release","-ID:\\Coding\\Qt\\StudentMessageManagemantSystem\\build\\Desktop_Qt_6_9_2_MinGW_64_bit-Release","-ID:\\App\\Qt\\6.9.2\\mingw_64\\mkspecs\\win32-g++","-isystem","D:\\App\\Qt\\Tools\\mingw1310_64\\lib\\gcc\\x86_64-w64-mingw32\\13.1.0\\include\\c++","-isystem","D:\\App\\Qt\\Tools\\mingw1310_64\\lib\\gcc\\x86_64-w64-mingw32\\13.1.0\\include\\c++\\x86_64-w64-mingw32","-isystem","D:\\App\\Qt\\Tools\\mingw1310_64\\lib\\gcc\\x86_64-w64-mingw32\\13.1.0\\include\\c++\\backward","-isystem","D:\\App\\Qt\\Tools\\QtCreator\\bin\\clang\\lib\\clang\\21\\include","-isystem","D:\\App\\Qt\\Tools\\mingw1310_64\\x86_64-w64-mingw32\\include","-fmessage-length=0","-fdiagnostics-show-note-include-stack","-fretain-comments-from-system-headers","-fmacro-backtrace-limit=0","-ferror-limit=1000","-x","c++","D:/Coding/Qt/StudentMessageManagemantSystem/main.cpp"],"directory":"D:/Coding/Qt/StudentMessageManagemantSystem/build/Desktop_Qt_6_9_2_MinGW_64_bit-Release/.qtc_clangd","file":"D:/Coding/Qt/StudentMessageManagemantSystem/main.cpp"},{"arguments":["clang","-Wno-documentation-unknown-command","-Wno-unknown-warning-option","-Wno-unknown-pragmas","-nostdinc","-nostdinc++","-std=gnu++1z","-Wall","-Wextra","-Wextra","-fexceptions","-mthreads","-fsyntax-only","-m64","--target=x86_64-w64-mingw32","-DUNICODE","-D_UNICODE","-DWIN32","-DMINGW_HAS_SECURE_API","-DQT_NO_DEBUG","-DQT_WIDGETS_LIB","-DQT_GUI_LIB","-DQT_CORE_LIB","-DQT_NEEDS_QMAIN","-DQ_CREATOR_RUN","-DQT_ANNOTATE_FUNCTION(x)=__attribute__((annotate(#x)))","-ID:\\App\\Qt\\Tools\\QtCreator\\share\\qtcreator\\cplusplus\\wrappedMingwHeaders","-ID:\\App\\Qt\\Tools\\QtCreator\\share\\qtcreator\\cplusplus\\wrappedQtHeaders","-ID:\\App\\Qt\\Tools\\QtCreator\\share\\qtcreator\\cplusplus\\wrappedQtHeaders\\QtCore","-ID:\\Coding\\Qt\\StudentMessageManagemantSystem","-ID:\\App\\Qt\\6.9.2\\mingw_64\\include","-ID:\\App\\Qt\\6.9.2\\mingw_64\\include\\QtWidgets","-ID:\\App\\Qt\\6.9.2\\mingw_64\\include\\QtGui","-ID:\\App\\Qt\\6.9.2\\mingw_64\\include\\QtCore","-ID:\\Coding\\Qt\\StudentMessageManagemantSystem\\build\\Desktop_Qt_6_9_2_MinGW_64_bit-Release\\release","-ID:\\Coding\\Qt\\StudentMessageManagemantSystem\\build\\Desktop_Qt_6_9_2_MinGW_64_bit-Release","-ID:\\App\\Qt\\6.9.2\\mingw_64\\mkspecs\\win32-g++","-isystem","D:\\App\\Qt\\Tools\\mingw1310_64\\lib\\gcc\\x86_64-w64-mingw32\\13.1.0\\include\\c++","-isystem","D:\\App\\Qt\\Tools\\mingw1310_64\\lib\\gcc\\x86_64-w64-mingw32\\13.1.0\\include\\c++\\x86_64-w64-mingw32","-isystem","D:\\App\\Qt\\Tools\\mingw1310_64\\lib\\gcc\\x86_64-w64-mingw32\\13.1.0\\include\\c++\\backward","-isystem","D:\\App\\Qt\\Tools\\QtCreator\\bin\\clang\\lib\\clang\\21\\include","-isystem","D:\\App\\Qt\\Tools\\mingw1310_64\\x86_64-w64-mingw32\\include","-fmessage-length=0","-fdiagnostics-show-note-include-stack","-fretain-comments-from-system-headers","-fmacro-backtrace-limit=0","-ferror-limit=1000","-x","c++","D:/Coding/Qt/StudentMessageManagemantSystem/mainwindow.cpp"],"directory":"D:/Coding/Qt/StudentMessageManagemantSystem/build/Desktop_Qt_6_9_2_MinGW_64_bit-Release/.qtc_clangd","file":"D:/Coding/Qt/StudentMessageManagemantSystem/mainwindow.cpp"},{"arguments":["clang","-Wno-documentation-unknown-command","-Wno-unknown-warning-option","-Wno-unknown-pragmas","-nostdinc","-nostdinc++","-std=gnu++1z","-Wall","-Wextra","-Wextra","-fexceptions","-mthreads","-fsyntax-only","-m64","--target=x86_64-w64-mingw32","-DUNICODE","-D_UNICODE","-DWIN32","-DMINGW_HAS_SECURE_API","-DQT_NO_DEBUG","-DQT_WIDGETS_LIB","-DQT_GUI_LIB","-DQT_CORE_LIB","-DQT_NEEDS_QMAIN","-DQ_CREATOR_RUN","-DQT_ANNOTATE_FUNCTION(x)=__attribute__((annotate(#x)))","-ID:\\App\\Qt\\Tools\\QtCreator\\share\\qtcreator\\cplusplus\\wrappedMingwHeaders","-ID:\\App\\Qt\\Tools\\QtCreator\\share\\qtcreator\\cplusplus\\wrappedQtHeaders","-ID:\\App\\Qt\\Tools\\QtCreator\\share\\qtcreator\\cplusplus\\wrappedQtHeaders\\QtCore","-ID:\\Coding\\Qt\\StudentMessageManagemantSystem","-ID:\\App\\Qt\\6.9.2\\mingw_64\\include","-ID:\\App\\Qt\\6.9.2\\mingw_64\\include\\QtWidgets","-ID:\\App\\Qt\\6.9.2\\mingw_64\\include\\QtGui","-ID:\\App\\Qt\\6.9.2\\mingw_64\\include\\QtCore","-ID:\\Coding\\Qt\\StudentMessageManagemantSystem\\build\\Desktop_Qt_6_9_2_MinGW_64_bit-Release\\release","-ID:\\Coding\\Qt\\StudentMessageManagemantSystem\\build\\Desktop_Qt_6_9_2_MinGW_64_bit-Release","-ID:\\App\\Qt\\6.9.2\\mingw_64\\mkspecs\\win32-g++","-isystem","D:\\App\\Qt\\Tools\\mingw1310_64\\lib\\gcc\\x86_64-w64-mingw32\\13.1.0\\include\\c++","-isystem","D:\\App\\Qt\\Tools\\mingw1310_64\\lib\\gcc\\x86_64-w64-mingw32\\13.1.0\\include\\c++\\x86_64-w64-mingw32","-isystem","D:\\App\\Qt\\Tools\\mingw1310_64\\lib\\gcc\\x86_64-w64-mingw32\\13.1.0\\include\\c++\\backward","-isystem","D:\\App\\Qt\\Tools\\QtCreator\\bin\\clang\\lib\\clang\\21\\include","-isystem","D:\\App\\Qt\\Tools\\mingw1310_64\\x86_64-w64-mingw32\\include","-fmessage-length=0","-fdiagnostics-show-note-include-stack","-fretain-comments-from-system-headers","-fmacro-backtrace-limit=0","-ferror-limit=1000","-x","c++","D:/Coding/Qt/StudentMessageManagemantSystem/StudentMessageManagementSystem.cpp"],"directory":"D:/Coding/Qt/StudentMessageManagemantSystem/build/Desktop_Qt_6_9_2_MinGW_64_bit-Release/.qtc_clangd","file":"D:/Coding/Qt/StudentMessageManagemantSystem/StudentMessageManagementSystem.cpp"},{"arguments":["clang","-Wno-documentation-unknown-command","-Wno-unknown-warning-option","-Wno-unknown-pragmas","-nostdinc","-nostdinc++","-std=gnu++1z","-Wall","-Wextra","-Wextra","-fexceptions","-mthreads","-fsyntax-only","-m64","--target=x86_64-w64-mingw32","-DUNICODE","-D_UNICODE","-DWIN32","-DMINGW_HAS_SECURE_API","-DQT_NO_DEBUG","-DQT_WIDGETS_LIB","-DQT_GUI_LIB","-DQT_CORE_LIB","-DQT_NEEDS_QMAIN","-DQ_CREATOR_RUN","-DQT_ANNOTATE_FUNCTION(x)=__attribute__((annotate(#x)))","-ID:\\App\\Qt\\Tools\\QtCreator\\share\\qtcreator\\cplusplus\\wrappedMingwHeaders","-ID:\\App\\Qt\\Tools\\QtCreator\\share\\qtcreator\\cplusplus\\wrappedQtHeaders","-ID:\\App\\Qt\\Tools\\QtCreator\\share\\qtcreator\\cplusplus\\wrappedQtHeaders\\QtCore","-ID:\\Coding\\Qt\\StudentMessageManagemantSystem","-ID:\\App\\Qt\\6.9.2\\mingw_64\\include","-ID:\\App\\Qt\\6.9.2\\mingw_64\\include\\QtWidgets","-ID:\\App\\Qt\\6.9.2\\mingw_64\\include\\QtGui","-ID:\\App\\Qt\\6.9.2\\mingw_64\\include\\QtCore","-ID:\\Coding\\Qt\\StudentMessageManagemantSystem\\build\\Desktop_Qt_6_9_2_MinGW_64_bit-Release\\release","-ID:\\Coding\\Qt\\StudentMessageManagemantSystem\\build\\Desktop_Qt_6_9_2_MinGW_64_bit-Release","-ID:\\App\\Qt\\6.9.2\\mingw_64\\mkspecs\\win32-g++","-isystem","D:\\App\\Qt\\Tools\\mingw1310_64\\lib\\gcc\\x86_64-w64-mingw32\\13.1.0\\include\\c++","-isystem","D:\\App\\Qt\\Tools\\mingw1310_64\\lib\\gcc\\x86_64-w64-mingw32\\13.1.0\\include\\c++\\x86_64-w64-mingw32","-isystem","D:\\App\\Qt\\Tools\\mingw1310_64\\lib\\gcc\\x86_64-w64-mingw32\\13.1.0\\include\\c++\\backward","-isystem","D:\\App\\Qt\\Tools\\QtCreator\\bin\\clang\\lib\\clang\\21\\include","-isystem","D:\\App\\Qt\\Tools\\mingw1310_64\\x86_64-w64-mingw32\\include","-fmessage-length=0","-fdiagnostics-show-note-include-stack","-fretain-comments-from-system-headers","-fmacro-backtrace-limit=0","-ferror-limit=1000","-x","c++-header","D:/Coding/Qt/StudentMessageManagemantSystem/mainwindow.h"],"directory":"D:/Coding/Qt/StudentMessageManagemantSystem/build/Desktop_Qt_6_9_2_MinGW_64_bit-Release/.qtc_clangd","file":"D:/Coding/Qt/StudentMessageManagemantSystem/mainwindow.h"},{"arguments":["clang","-Wno-documentation-unknown-command","-Wno-unknown-warning-option","-Wno-unknown-pragmas","-nostdinc","-nostdinc++","-std=gnu++1z","-Wall","-Wextra","-Wextra","-fexceptions","-mthreads","-fsyntax-only","-m64","--target=x86_64-w64-mingw32","-DUNICODE","-D_UNICODE","-DWIN32","-DMINGW_HAS_SECURE_API","-DQT_NO_DEBUG","-DQT_WIDGETS_LIB","-DQT_GUI_LIB","-DQT_CORE_LIB","-DQT_NEEDS_QMAIN","-DQ_CREATOR_RUN","-DQT_ANNOTATE_FUNCTION(x)=__attribute__((annotate(#x)))","-ID:\\App\\Qt\\Tools\\QtCreator\\share\\qtcreator\\cplusplus\\wrappedMingwHeaders","-ID:\\App\\Qt\\Tools\\QtCreator\\share\\qtcreator\\cplusplus\\wrappedQtHeaders","-ID:\\App\\Qt\\Tools\\QtCreator\\share\\qtcreator\\cplusplus\\wrappedQtHeaders\\QtCore","-ID:\\Coding\\Qt\\StudentMessageManagemantSystem","-ID:\\App\\Qt\\6.9.2\\mingw_64\\include","-ID:\\App\\Qt\\6.9.2\\mingw_64\\include\\QtWidgets","-ID:\\App\\Qt\\6.9.2\\mingw_64\\include\\QtGui","-ID:\\App\\Qt\\6.9.2\\mingw_64\\include\\QtCore","-ID:\\Coding\\Qt\\StudentMessageManagemantSystem\\build\\Desktop_Qt_6_9_2_MinGW_64_bit-Release\\release","-ID:\\Coding\\Qt\\StudentMessageManagemantSystem\\build\\Desktop_Qt_6_9_2_MinGW_64_bit-Release","-ID:\\App\\Qt\\6.9.2\\mingw_64\\mkspecs\\win32-g++","-isystem","D:\\App\\Qt\\Tools\\mingw1310_64\\lib\\gcc\\x86_64-w64-mingw32\\13.1.0\\include\\c++","-isystem","D:\\App\\Qt\\Tools\\mingw1310_64\\lib\\gcc\\x86_64-w64-mingw32\\13.1.0\\include\\c++\\x86_64-w64-mingw32","-isystem","D:\\App\\Qt\\Tools\\mingw1310_64\\lib\\gcc\\x86_64-w64-mingw32\\13.1.0\\include\\c++\\backward","-isystem","D:\\App\\Qt\\Tools\\QtCreator\\bin\\clang\\lib\\clang\\21\\include","-isystem","D:\\App\\Qt\\Tools\\mingw1310_64\\x86_64-w64-mingw32\\include","-fmessage-length=0","-fdiagnostics-show-note-include-stack","-fretain-comments-from-system-headers","-fmacro-backtrace-limit=0","-ferror-limit=1000","-x","c++-header","D:/Coding/Qt/StudentMessageManagemantSystem/student.h"],"directory":"D:/Coding/Qt/StudentMessageManagemantSystem/build/Desktop_Qt_6_9_2_MinGW_64_bit-Release/.qtc_clangd","file":"D:/Coding/Qt/StudentMessageManagemantSystem/student.h"},{"arguments":["clang","-Wno-documentation-unknown-command","-Wno-unknown-warning-option","-Wno-unknown-pragmas","-nostdinc","-nostdinc++","-std=gnu++1z","-Wall","-Wextra","-Wextra","-fexceptions","-mthreads","-fsyntax-only","-m64","--target=x86_64-w64-mingw32","-DUNICODE","-D_UNICODE","-DWIN32","-DMINGW_HAS_SECURE_API","-DQT_NO_DEBUG","-DQT_WIDGETS_LIB","-DQT_GUI_LIB","-DQT_CORE_LIB","-DQT_NEEDS_QMAIN","-DQ_CREATOR_RUN","-DQT_ANNOTATE_FUNCTION(x)=__attribute__((annotate(#x)))","-ID:\\App\\Qt\\Tools\\QtCreator\\share\\qtcreator\\cplusplus\\wrappedMingwHeaders","-ID:\\App\\Qt\\Tools\\QtCreator\\share\\qtcreator\\cplusplus\\wrappedQtHeaders","-ID:\\App\\Qt\\Tools\\QtCreator\\share\\qtcreator\\cplusplus\\wrappedQtHeaders\\QtCore","-ID:\\Coding\\Qt\\StudentMessageManagemantSystem","-ID:\\App\\Qt\\6.9.2\\mingw_64\\include","-ID:\\App\\Qt\\6.9.2\\mingw_64\\include\\QtWidgets","-ID:\\App\\Qt\\6.9.2\\mingw_64\\include\\QtGui","-ID:\\App\\Qt\\6.9.2\\mingw_64\\include\\QtCore","-ID:\\Coding\\Qt\\StudentMessageManagemantSystem\\build\\Desktop_Qt_6_9_2_MinGW_64_bit-Release\\release","-ID:\\Coding\\Qt\\StudentMessageManagemantSystem\\build\\Desktop_Qt_6_9_2_MinGW_64_bit-Release","-ID:\\App\\Qt\\6.9.2\\mingw_64\\mkspecs\\win32-g++","-isystem","D:\\App\\Qt\\Tools\\mingw1310_64\\lib\\gcc\\x86_64-w64-mingw32\\13.1.0\\include\\c++","-isystem","D:\\App\\Qt\\Tools\\mingw1310_64\\lib\\gcc\\x86_64-w64-mingw32\\13.1.0\\include\\c++\\x86_64-w64-mingw32","-isystem","D:\\App\\Qt\\Tools\\mingw1310_64\\lib\\gcc\\x86_64-w64-mingw32\\13.1.0\\include\\c++\\backward","-isystem","D:\\App\\Qt\\Tools\\QtCreator\\bin\\clang\\lib\\clang\\21\\include","-isystem","D:\\App\\Qt\\Tools\\mingw1310_64\\x86_64-w64-mingw32\\include","-fmessage-length=0","-fdiagnostics-show-note-include-stack","-fretain-comments-from-system-headers","-fmacro-backtrace-limit=0","-ferror-limit=1000","-x","c++-header","D:/Coding/Qt/StudentMessageManagemantSystem/binarysearchtree.h"],"directory":"D:/Coding/Qt/StudentMessageManagemantSystem/build/Desktop_Qt_6_9_2_MinGW_64_bit-Release/.qtc_clangd","file":"D:/Coding/Qt/StudentMessageManagemantSystem/binarysearchtree.h"},{"arguments":["clang","-Wno-documentation-unknown-command","-Wno-unknown-warning-option","-Wno-unknown-pragmas","-nostdinc","-nostdinc++","-std=gnu++1z","-Wall","-Wextra","-Wextra","-fexceptions","-mthreads","-fsyntax-only","-m64","--target=x86_64-w64-mingw32","-DUNICODE","-D_UNICODE","-DWIN32","-DMINGW_HAS_SECURE_API","-DQT_NO_DEBUG","-DQT_WIDGETS_LIB","-DQT_GUI_LIB","-DQT_CORE_LIB","-DQT_NEEDS_QMAIN","-DQ_CREATOR_RUN","-DQT_ANNOTATE_FUNCTION(x)=__attribute__((annotate(#x)))","-ID:\\App\\Qt\\Tools\\QtCreator\\share\\qtcreator\\cplusplus\\wrappedMingwHeaders","-ID:\\App\\Qt\\Tools\\QtCreator\\share\\qtcreator\\cplusplus\\wrappedQtHeaders","-ID:\\App\\Qt\\Tools\\QtCreator\\share\\qtcreator\\cplusplus\\wrappedQtHeaders\\QtCore","-ID:\\Coding\\Qt\\StudentMessageManagemantSystem","-ID:\\App\\Qt\\6.9.2\\mingw_64\\include","-ID:\\App\\Qt\\6.9.2\\mingw_64\\include\\QtWidgets","-ID:\\App\\Qt\\6.9.2\\mingw_64\\include\\QtGui","-ID:\\App\\Qt\\6.9.2\\mingw_64\\include\\QtCore","-ID:\\Coding\\Qt\\StudentMessageManagemantSystem\\build\\Desktop_Qt_6_9_2_MinGW_64_bit-Release\\release","-ID:\\Coding\\Qt\\StudentMessageManagemantSystem\\build\\Desktop_Qt_6_9_2_MinGW_64_bit-Release","-ID:\\App\\Qt\\6.9.2\\mingw_64\\mkspecs\\win32-g++","-isystem","D:\\App\\Qt\\Tools\\mingw1310_64\\lib\\gcc\\x86_64-w64-mingw32\\13.1.0\\include\\c++","-isystem","D:\\App\\Qt\\Tools\\mingw1310_64\\lib\\gcc\\x86_64-w64-mingw32\\13.1.0\\include\\c++\\x86_64-w64-mingw32","-isystem","D:\\App\\Qt\\Tools\\mingw1310_64\\lib\\gcc\\x86_64-w64-mingw32\\13.1.0\\include\\c++\\backward","-isystem","D:\\App\\Qt\\Tools\\QtCreator\\bin\\clang\\lib\\clang\\21\\include","-isystem","D:\\App\\Qt\\Tools\\mingw1310_64\\x86_64-w64-mingw32\\include","-fmessage-length=0","-fdiagnostics-show-note-include-stack","-fretain-comments-from-system-headers","-fmacro-backtrace-limit=0","-ferror-limit=1000","-x","c++-header","D:/Coding/Qt/StudentMessageManagemantSystem/StudentMessageManagementSystem.h"],"directory":"D:/Coding/Qt/StudentMessageManagemantSystem/build/Desktop_Qt_6_9_2_MinGW_64_bit-Release/.qtc_clangd","file":"D:/Coding/Qt/StudentMessageManagemantSystem/StudentMessageManagementSystem.h"},{"arguments":["clang","-Wno-documentation-unknown-command","-Wno-unknown-warning-option","-Wno-unknown-pragmas","-nostdinc","-nostdinc++","-std=gnu++1z","-Wall","-Wextra","-Wextra","-fexceptions","-mthreads","-fsyntax-only","-m64","--target=x86_64-w64-mingw32","-DUNICODE","-D_UNICODE","-DWIN32","-DMINGW_HAS_SECURE_API","-DQT_NO_DEBUG","-DQT_WIDGETS_LIB","-DQT_GUI_LIB","-DQT_CORE_LIB","-DQT_NEEDS_QMAIN","-DQ_CREATOR_RUN","-DQT_ANNOTATE_FUNCTION(x)=__attribute__((annotate(#x)))","-ID:\\App\\Qt\\Tools\\QtCreator\\share\\qtcreator\\cplusplus\\wrappedMingwHeaders","-ID:\\App\\Qt\\Tools\\QtCreator\\share\\qtcreator\\cplusplus\\wrappedQtHeaders","-ID:\\App\\Qt\\Tools\\QtCreator\\share\\qtcreator\\cplusplus\\wrappedQtHeaders\\QtCore","-ID:\\Coding\\Qt\\StudentMessageManagemantSystem","-ID:\\App\\Qt\\6.9.2\\mingw_64\\include","-ID:\\App\\Qt\\6.9.2\\mingw_64\\include\\QtWidgets","-ID:\\App\\Qt\\6.9.2\\mingw_64\\include\\QtGui","-ID:\\App\\Qt\\6.9.2\\mingw_64\\include\\QtCore","-ID:\\Coding\\Qt\\StudentMessageManagemantSystem\\build\\Desktop_Qt_6_9_2_MinGW_64_bit-Release\\release","-ID:\\Coding\\Qt\\StudentMessageManagemantSystem\\build\\Desktop_Qt_6_9_2_MinGW_64_bit-Release","-ID:\\App\\Qt\\6.9.2\\mingw_64\\mkspecs\\win32-g++","-isystem","D:\\App\\Qt\\Tools\\mingw1310_64\\lib\\gcc\\x86_64-w64-mingw32\\13.1.0\\include\\c++","-isystem","D:\\App\\Qt\\Tools\\mingw1310_64\\lib\\gcc\\x86_64-w64-mingw32\\13.1.0\\include\\c++\\x86_64-w64-mingw32","-isystem","D:\\App\\Qt\\Tools\\mingw1310_64\\lib\\gcc\\x86_64-w64-mingw32\\13.1.0\\include\\c++\\backward","-isystem","D:\\App\\Qt\\Tools\\QtCreator\\bin\\clang\\lib\\clang\\21\\include","-isystem","D:\\App\\Qt\\Tools\\mingw1310_64\\x86_64-w64-mingw32\\include","-fmessage-length=0","-fdiagnostics-show-note-include-stack","-fretain-comments-from-system-headers","-fmacro-backtrace-limit=0","-ferror-limit=1000","-x","c++-header","D:/Coding/Qt/StudentMessageManagemantSystem/build/Desktop_Qt_6_9_2_MinGW_64_bit-Release/ui_StudentMessageManagementSystem.h"],"directory":"D:/Coding/Qt/StudentMessageManagemantSystem/build/Desktop_Qt_6_9_2_MinGW_64_bit-Release/.qtc_clangd","file":"D:/Coding/Qt/StudentMessageManagemantSystem/build/Desktop_Qt_6_9_2_MinGW_64_bit-Release/ui_StudentMessageManagementSystem.h"}]